flask_datepicker/__init__.py
flask_datepicker/about.py
flask_datepicker/constants.py
flask_datepicker/main.py
flask_datepicker/utils.py
Flask_Datepicker-0.16.dist-info/LICENSE.txt
Flask_Datepicker-0.16.dist-info/METADATA
Flask_Datepicker-0.16.dist-info/WHEEL
Flask_Datepicker-0.16.dist-info/top_level.txt
Flask_Datepicker-0.16.dist-info/RECORD
