Metadata-Version: 2.1
Name: Flask-Datepicker
Version: 0.16
Summary: A Flask extension for jQueryUI DatePicker.
Home-page: https://github.com/mrf345/flask_datepicker/
Download-URL: https://github.com/mrf345/flask_datepicker/archive/0.16.tar.gz
Author: Mohamed Feddad
Author-email: mrf345@gmail.com
License: MIT
Keywords: flask,extension,date,picker,jquery-ui,datepicker
Platform: any
Classifier: Programming Language :: Python :: 3.7
Classifier: Programming Language :: Python :: 3.8
Classifier: Programming Language :: Python :: 3.9
Classifier: Programming Language :: Python :: 3.10
Classifier: Programming Language :: Python :: 3.11
Classifier: Programming Language :: Python :: 3.12
Classifier: Environment :: Web Environment
Classifier: Intended Audience :: Developers
Classifier: License :: OSI Approved :: MIT License
Classifier: Operating System :: OS Independent
Classifier: Programming Language :: Python
Classifier: Topic :: Internet :: WWW/HTTP :: Dynamic Content
Classifier: Topic :: Software Development :: Libraries :: Python Modules
License-File: LICENSE.txt
Requires-Dist: Flask
Requires-Dist: Flask-Bootstrap
Requires-Dist: MarkupSafe
